odoo/addons/pos_edit_order_line/README.rst
odoo/addons/pos_edit_order_line/__init__.py
odoo/addons/pos_edit_order_line/__manifest__.py
odoo/addons/pos_edit_order_line/i18n/es.po
odoo/addons/pos_edit_order_line/i18n/it.po
odoo/addons/pos_edit_order_line/i18n/pos_edit_order_line.pot
odoo/addons/pos_edit_order_line/models/__init__.py
odoo/addons/pos_edit_order_line/models/pos_config.py
odoo/addons/pos_edit_order_line/models/res_config_settings.py
odoo/addons/pos_edit_order_line/readme/CONFIGURE.rst
odoo/addons/pos_edit_order_line/readme/CONTRIBUTORS.rst
odoo/addons/pos_edit_order_line/readme/DESCRIPTION.rst
odoo/addons/pos_edit_order_line/readme/HISTORY.rst
odoo/addons/pos_edit_order_line/static/description/icon.png
odoo/addons/pos_edit_order_line/static/description/index.html
odoo/addons/pos_edit_order_line/static/description/pos_edit_order_line.png
odoo/addons/pos_edit_order_line/static/src/css/pos.css
odoo/addons/pos_edit_order_line/static/src/js/EditOrderButton.js
odoo/addons/pos_edit_order_line/static/src/js/EditOrderLineInput.js
odoo/addons/pos_edit_order_line/static/src/js/EditOrderPopup.js
odoo/addons/pos_edit_order_line/static/src/xml/EditOrderButton.xml
odoo/addons/pos_edit_order_line/static/src/xml/EditOrderLineInput.xml
odoo/addons/pos_edit_order_line/static/src/xml/EditOrderPopup.xml
odoo/addons/pos_edit_order_line/views/res_config_settings_view.xml
odoo_addon_pos_edit_order_line-16.0.1.0.1.4.dist-info/METADATA
odoo_addon_pos_edit_order_line-16.0.1.0.1.4.dist-info/WHEEL
odoo_addon_pos_edit_order_line-16.0.1.0.1.4.dist-info/top_level.txt
odoo_addon_pos_edit_order_line-16.0.1.0.1.4.dist-info/RECORD
